ottr_force_save_labextension/__init__.py
ottr_force_save_labextension/_version.py
ottr_force_save_labextension-0.1.1.data/data/share/jupyter/labextensions/ottr-force-save-labextension/package.json
ottr_force_save_labextension-0.1.1.data/data/share/jupyter/labextensions/ottr-force-save-labextension/static/568.c3d8e2c032c1ac496fc6.js
ottr_force_save_labextension-0.1.1.data/data/share/jupyter/labextensions/ottr-force-save-labextension/static/747.21a8a7d6474ea898711f.js
ottr_force_save_labextension-0.1.1.data/data/share/jupyter/labextensions/ottr-force-save-labextension/static/remoteEntry.04f3921e1efed6581741.js
ottr_force_save_labextension-0.1.1.data/data/share/jupyter/labextensions/ottr-force-save-labextension/static/style.js
ottr_force_save_labextension-0.1.1.data/data/share/jupyter/labextensions/ottr-force-save-labextension/static/third-party-licenses.json
ottr_force_save_labextension-0.1.1.data/data/share/jupyter/labextensions/ottr-force-save-labextension/install.json
ottr_force_save_labextension-0.1.1.dist-info/METADATA
ottr_force_save_labextension-0.1.1.dist-info/WHEEL
ottr_force_save_labextension-0.1.1.dist-info/licenses/LICENSE
ottr_force_save_labextension-0.1.1.dist-info/RECORD
