Metadata-Version: 2.1
Name: ottr_force_save_labextension
Version: 0.1.1
Summary: A JupyterLab extension for force-saving notebooks from ottr, the Otter-Grader R client.
Project-URL: Homepage, https://github.com/chrispyles/ottr-force-save-labextension
Project-URL: Bug Tracker, https://github.com/chrispyles/ottr-force-save-labextension/issues
Project-URL: Repository, https://github.com/chrispyles/ottr-force-save-labextension.git
Author-email: Chris Pyles <cpyles@berkeley.edu>
License: BSD 3-Clause License
License-File: LICENSE
Classifier: Framework :: Jupyter
Classifier: Framework :: Jupyter :: JupyterLab
Classifier: Framework :: Jupyter :: JupyterLab :: 4
Classifier: Framework :: Jupyter :: JupyterLab :: Extensions
Classifier: Framework :: Jupyter :: JupyterLab :: Extensions :: Prebuilt
Classifier: License :: OSI Approved :: BSD License
Classifier: Programming Language :: Python
Classifier: Programming Language :: Python :: 3
Classifier: Programming Language :: Python :: 3.8
Classifier: Programming Language :: Python :: 3.9
Classifier: Programming Language :: Python :: 3.10
Classifier: Programming Language :: Python :: 3.11
Classifier: Programming Language :: Python :: 3.12
Requires-Python: >=3.8
